{"card_name": "Insect DICE AND FLIES", "color": "R", "rarity": "common", "type": "Token Creature \u2013 Insect", "number": 33, "color_identity": "R", "cost": "", "rules_text": "Flying\nDecayed [i](This creature can\u2019t block. When it attacks, sacrifice it at end of combat.)[/i] [i](This creature can\u2019t block. When it attacks, sacrifice it at end of combat.)[/i]", "pt": "1/1", "special_text": "", "shape": "token", "set": "JUMP\u2605", "loyalty": "", "notes": "!related Horrid Polycephalus;Festering Gorepile;Duke of Flies;Guppy Lost Companion;Apollyon, Locust Host;Apollyon, Locust Host;Apollyon, Locust Host;\n!exportname Insect DICE AND FLIES\n!tag pack-name-diceandflies\n!sort diceandflies"}