{"card_name": "Benevolent Prancer", "color": "G", "rarity": "uncommon", "type": "Creature \u2013 Horse Beast", "number": 547, "color_identity": "G", "cost": "{2}{G}", "rules_text": "Flourish 4/5 \u2013 {3}{G}{G} [i](You may cast this for its flourish cost or pay that cost as a sorcery to have its base size become 4/5.)[/i]\nWhenever this creature attacks, put a +1/+1 counter on target creature you control with lesser power.", "pt": "2/3", "special_text": "", "shape": "normal", "set": "JUMP\u2605", "loyalty": "", "notes": "!tag pack-name-life\n!tag pack-cycle-incarnation\n!sort life"}