{"card_name": "Nature's Empath", "color": "RG", "rarity": "uncommon", "type": "Creature \u2013 Human Shaman", "number": 789, "color_identity": "RG", "cost": "{1}{RG}", "rules_text": "When this creature enters, you may raze. [i](To raze, sacrifice a land or exile a land card from your graveyard.)[/i]\nAt the beginning of combat on your turn, this creature gets +X/+X until end of turn, where X is the number of lands cards your own in exile or in your graveyard.", "pt": "2/2", "special_text": "", "shape": "normal", "set": "JUMP\u2605", "loyalty": "", "notes": "!tag pack-name-gruul\n!tag pack-cycle-ravnica\n!sort gruul"}